tests/__init__.py
tests/test_library.py
tpm_fingerprint_lib/__init__.py
tpm_fingerprint_lib/audit_logger.py
tpm_fingerprint_lib/cli.py
tpm_fingerprint_lib/config.py
tpm_fingerprint_lib/consequence_handler.py
tpm_fingerprint_lib/exceptions.py
tpm_fingerprint_lib/fingerprint_engine.py
tpm_fingerprint_lib/offline_verifier.py
tpm_fingerprint_lib/policy_engine.py
tpm_fingerprint_lib/tpm_ops.py
tpm_fingerprint_lib-1.0.0.dist-info/licenses/LICENSE
tpm_fingerprint_lib-1.0.0.dist-info/METADATA
tpm_fingerprint_lib-1.0.0.dist-info/WHEEL
tpm_fingerprint_lib-1.0.0.dist-info/entry_points.txt
tpm_fingerprint_lib-1.0.0.dist-info/top_level.txt
tpm_fingerprint_lib-1.0.0.dist-info/RECORD
