Metadata-Version: 2.4
Name: tpm-fingerprint-lib
Version: 1.0.0
Summary: Comprehensive TPM-based device fingerprinting with cryptographically enforced governance
Home-page: https://github.com/yourusername/tpm-fingerprint-lib
Author: TPM Fingerprint Library
Author-email: your.email@example.com
Project-URL: Bug Reports, https://github.com/yourusername/tpm-fingerprint-lib/issues
Project-URL: Source, https://github.com/yourusername/tpm-fingerprint-lib
Project-URL: Documentation, https://tpm-fingerprint-lib.readthedocs.io/
Keywords: tpm fingerprint security attestation hardware cryptography policy enforcement
Classifier: Development Status :: 4 - Beta
Classifier: Intended Audience :: Developers
Classifier: Topic :: Security :: Cryptography
Classifier: Topic :: System :: Hardware
Classifier: License :: OSI Approved :: MIT License
Classifier: Programming Language :: Python :: 3
Classifier: Programming Language :: Python :: 3.8
Classifier: Programming Language :: Python :: 3.9
Classifier: Programming Language :: Python :: 3.10
Classifier: Programming Language :: Python :: 3.11
Classifier: Operating System :: OS Independent
Classifier: Operating System :: Microsoft :: Windows
Classifier: Operating System :: POSIX :: Linux
Requires-Python: >=3.8
License-File: LICENSE
Requires-Dist: cryptography>=41.0.0
Requires-Dist: pywin32>=305; sys_platform == "win32"
Requires-Dist: WMI>=1.5.1; sys_platform == "win32"
Provides-Extra: dev
Requires-Dist: pytest>=7.4.0; extra == "dev"
Requires-Dist: pytest-cov>=4.1.0; extra == "dev"
Requires-Dist: black>=23.0.0; extra == "dev"
Requires-Dist: mypy>=1.5.0; extra == "dev"
Requires-Dist: pylint>=2.17.0; extra == "dev"
Provides-Extra: docs
Requires-Dist: sphinx>=7.0.0; extra == "docs"
Requires-Dist: sphinx-rtd-theme>=1.3.0; extra == "docs"
Provides-Extra: enhanced
Provides-Extra: pqc
Dynamic: author
Dynamic: author-email
Dynamic: classifier
Dynamic: description
Dynamic: description-content-type
Dynamic: home-page
Dynamic: keywords
Dynamic: license-file
Dynamic: project-url
Dynamic: provides-extra
Dynamic: requires-dist
Dynamic: requires-python
Dynamic: summary
